learntools/__init__.py
learntools/core/__init__.py
learntools/core/asserts.py
learntools/core/colors.py
learntools/core/constants.py
learntools/core/exceptions.py
learntools/core/globals_binder.py
learntools/core/multiproblem.py
learntools/core/problem.py
learntools/core/problem_view.py
learntools/core/richtext.py
learntools/core/tracking.py
learntools/core/utils.py
learntools/python/__init__.py
learntools/python/blackjack.py
learntools/python/ex1.py
learntools/python/ex2.py
learntools/python/ex3.py
learntools/python/ex4.py
learntools/python/ex5.py
learntools/python/ex6.py
learntools/python/ex7.py
learntools/python/jimmy_slots.py
learntools/python/luigi_analysis.py
learntools/python/quickdraw.py
learntools/python/roulette.py
learntools/python/solns/__init__.py
learntools/python/solns/blackjack_gt.py
learntools/python/solns/diamond.py
learntools/python/solns/jimmygraph.py
learntools/python/solns/multi_word_search.py
learntools/python/solns/roulette_analysis.py
learntools/python/solns/word_search.py
learntools/thebridge/__init__.py
learntools/thebridge/__main__.py
learntools/thebridge/python_basics_i.py
learntools/thebridge/python_basics_ii.py
thebridge_autocheck-1.2.0.dist-info/LICENSE
thebridge_autocheck-1.2.0.dist-info/METADATA
thebridge_autocheck-1.2.0.dist-info/WHEEL
thebridge_autocheck-1.2.0.dist-info/top_level.txt
thebridge_autocheck-1.2.0.dist-info/RECORD
