Metadata-Version: 2.1
Name: thebridge-autocheck
Version: 1.2.0
Summary: Automatic correction for The Bridge Exercises
Author-email: Alberto Becerra Tomé <alberto.becerra@thebridgeschool.es>
License: Work In Process
Project-URL: Homepage, https://github.com/AlbertoBecerraTB/TheBridge-AutoCheck
Keywords: exercises,learn,tutorial
Classifier: Programming Language :: Python
Classifier: Programming Language :: Python :: 3
Requires-Python: >=3.6
License-File: LICENSE
Requires-Dist: pandas
Requires-Dist: tomli
Requires-Dist: ipywidgets (==8.0.2)
